neo_toolbox/create_owner_bytes.py
neo_toolbox/create_update_invocation_file.py
neo_toolbox/data_transformation.py
neo_toolbox-0.1.6.dist-info/WHEEL
neo_toolbox-0.1.6.dist-info/METADATA
neo_toolbox-0.1.6.dist-info/RECORD
